anylearning/__init__.py
anylearning/anylabeling2yolo.py
anylearning/converter.py
anylearning-0.0.3.dist-info/METADATA
anylearning-0.0.3.dist-info/WHEEL
anylearning-0.0.3.dist-info/top_level.txt
anylearning-0.0.3.dist-info/RECORD
